test1266/__init__.py
test1266/live-scraping-firebase-adminsdk-gck9g-011e4f00e1.json
test1266/script_tracker.py
test1266-0.1.dist-info/METADATA
test1266-0.1.dist-info/WHEEL
test1266-0.1.dist-info/top_level.txt
test1266-0.1.dist-info/RECORD
